Workbook
Name Slicer_Product_Type: #N/A
Name Slicer_Routes: #N/A
Name Slicer_Shipping_Carriers: #N/A
Name Slicer_SKU: #N/A
Name Slicer_Transportation_Modes: #N/A

Sheet 01_README
A1: SUPPLY CHAIN ANALYSIS DASHBOARD
A3: Author: Mgbonye Winnifred Ebele
A4: Tool Used: Microsoft Excel
A6: OBJECTIVE
A7: To analyze supply chain performance by evaluating revenue, cost, profit, inventory and logistics efficiency in order to identify optimization opportunities.
A9: DATASET DESCRIPTION
A10: The dataset contains supply chain data from a fashion and beauty startup, including product types, SKUs, revenue, costs, shipping details and defect rates.
A12: DATA CLEANING STEPS
A13: • Removed inconsistencies using TRIM and PROPER functions.
A14: • Checked for missing values and duplicates (none found)
A15: • Standardized column names using snake_case
A16: • Assigned appropriate data types
... A67: Overall, this dashboard demonstrates the importance of evaluating both profitability and operational efficiency, providing actionable insights to support better decision-making and supply chain optimization.

Sheet 02_RAW_DATA
A1: Product type | B1: SKU | C1: Price | D1: Availability | E1: Number of products sold | F1: Revenue generated | G1: Customer demographics | H1: Stock levels | I1: Lead times | J1: Order quantities | K1: Shipping times | L1: Shipping carriers | M1: Shipping costs | N1: Supplier name | O1: Location | P1: Lead time | Q1: Production volumes | R1: Manufacturing lead time | S1: Manufacturing costs | T1: Inspection results | U1: Defect rates | V1: Transportation modes | W1: Routes | X1: Costs
A2: haircare | B2: SKU0 | C2: 69.808006 | D2: 55 | E2: 802 | F2: 8661.9968 | G2: Non-binary | H2: 58 | I2: 7 | J2: 96 | K2: 4 | L2: Carrier B | M2: 2.9565721 | N2: Supplier 3 | O2: Mumbai | P2: 29 | Q2: 215 | R2: 29 | S2: 46.279879 | T2: Pending | U2: 0.22641036 | V2: Road | W2: Route B | X2: 187.75208
A3: skincare | B3: SKU1 | C3: 14.843523 | D3: 95 | E3: 736 | F3: 7460.9001 | G3: Female | H3: 53 | I3: 30 | J3: 37 | K3: 2 | L3: Carrier A | M3: 9.7165748 | N3: Supplier 3 | O3: Mumbai | P3: 23 | Q3: 517 | R3: 30 | S3: 33.616769 | T3: Pending | U3: 4.854068 | V3: Road | W3: Route B | X3: 503.06558
A4: haircare | B4: SKU2 | C4: 11.319683 | D4: 34 | E4: 8 | F4: 9577.7496 | G4: Unknown | H4: 1 | I4: 10 | J4: 88 | K4: 2 | L4: Carrier B | M4: 8.0544793 | N4: Supplier 1 | O4: Mumbai | P4: 12 | Q4: 971 | R4: 27 | S4: 30.688019 | T4: Pending | U4: 4.5805926 | V4: Air | W4: Route C | X4: 141.92028
A5: skincare | B5: SKU3 | C5: 61.163343 | D5: 68 | E5: 83 | F5: 7766.8364 | G5: Non-binary | H5: 23 | I5: 13 | J5: 59 | K5: 6 | L5: Carrier C | M5: 1.7295686 | N5: Supplier 5 | O5: Kolkata | P5: 24 | Q5: 937 | R5: 18 | S5: 35.624741 | T5: Fail | U5: 4.7466486 | V5: Rail | W5: Route A | X5: 254.77616
A6: skincare | B6: SKU4 | C6: 4.805496 | D6: 26 | E6: 871 | F6: 2686.5052 | G6: Non-binary | H6: 5 | I6: 3 | J6: 56 | K6: 8 | L6: Carrier A | M6: 3.8905479 | N6: Supplier 1 | O6: Delhi | P6: 5 | Q6: 414 | R6: 3 | S6: 92.065161 | T6: Fail | U6: 3.1455795 | V6: Air | W6: Route A | X6: 923.44063
A7: haircare | B7: SKU5 | C7: 1.699976 | D7: 87 | E7: 147 | F7: 2828.3487 | G7: Non-binary | H7: 90 | I7: 27 | J7: 66 | K7: 3 | L7: Carrier B | M7: 4.4440989 | N7: Supplier 4 | O7: Bangalore | P7: 10 | Q7: 104 | R7: 17 | S7: 56.766476 | T7: Fail | U7: 2.7791935 | V7: Road | W7: Route A | X7: 235.46124
A8: skincare | B8: SKU6 | C8: 4.0783329 | D8: 48 | E8: 65 | F8: 7823.4766 | G8: Male | H8: 11 | I8: 15 | J8: 58 | K8: 8 | L8: Carrier C | M8: 3.8807633 | N8: Supplier 3 | O8: Kolkata | P8: 14 | Q8: 314 | R8: 24 | S8: 1.0850686 | T8: Pending | U8: 1.0009106 | V8: Sea | W8: Route A | X8: 134.3691
A9: cosmetics | B9: SKU7 | C9: 42.958384 | D9: 59 | E9: 426 | F9: 8496.1038 | G9: Female | H9: 93 | I9: 17 | J9: 11 | K9: 1 | L9: Carrier B | M9: 2.3483388 | N9: Supplier 4 | O9: Bangalore | P9: 22 | Q9: 564 | R9: 1 | S9: 99.466109 | T9: Fail | U9: 0.39817719 | V9: Road | W9: Route C | X9: 802.05631
A10: cosmetics | B10: SKU8 | C10: 68.717597 | D10: 78 | E10: 150 | F10: 7517.3632 | G10: Female | H10: 5 | I10: 10 | J10: 15 | K10: 7 | L10: Carrier C | M10: 3.4047339 | N10: Supplier 4 | O10: Mumbai | P10: 13 | Q10: 769 | R10: 8 | S10: 11.423027 | T10: Pending | U10: 2.7098627 | V10: Sea | W10: Route B | X10: 505.55713
A11: skincare | B11: SKU9 | C11: 64.015733 | D11: 35 | E11: 980 | F11: 4971.146 | G11: Unknown | H11: 14 | I11: 27 | J11: 83 | K11: 1 | L11: Carrier A | M11: 7.1666453 | N11: Supplier 2 | O11: Chennai | P11: 29 | Q11: 963 | R11: 23 | S11: 47.957602 | T11: Pending | U11: 3.8446145 | V11: Rail | W11: Route B | X11: 995.92946
A12: skincare | B12: SKU10 | C12: 15.707796 | D12: 11 | E12: 996 | F12: 2330.9658 | G12: Non-binary | H12: 51 | I12: 13 | J12: 80 | K12: 2 | L12: Carrier C | M12: 8.6732112 | N12: Supplier 5 | O12: Kolkata | P12: 18 | Q12: 830 | R12: 5 | S12: 96.527353 | T12: Pass | U12: 1.7273139 | V12: Road | W12: Route B | X12: 806.10318
A13: skincare | B13: SKU11 | C13: 90.63546 | D13: 95 | E13: 960 | F13: 6099.9441 | G13: Female | H13: 46 | I13: 23 | J13: 60 | K13: 1 | L13: Carrier A | M13: 4.5239431 | N13: Supplier 2 | O13: Kolkata | P13: 28 | Q13: 362 | R13: 11 | S13: 27.592363 | T13: Pending | U13: 0.021169821 | V13: Air | W13: Route A | X13: 126.72303
... A101: haircare | B101: SKU99 | C101: 68.517833 | D101: 17 | E101: 627 | F101: 9185.1858 | G101: Unknown | H101: 55 | I101: 8 | J101: 59 | K101: 6 | L101: Carrier B | M101: 1.3110238 | N101: Supplier 2 | O101: Chennai | P101: 29 | Q101: 921 | R101: 2 | S101: 38.072899 | T101: Fail | U101: 0.34602729 | V101: Rail | W101: Route B | X101: 210.74301

Sheet 03_WORKINGS
A1: Product type | B1: Product type2 | C1: SKU | D1: Price | E1: Availability | F1: Number of products sold | G1: Revenue generated | H1: Customer demographics | I1: Stock levels | J1: Lead times | K1: Order quantities | L1: Shipping times | M1: Shipping carriers | N1: Shipping costs | O1: Supplier name | P1: Location | Q1: Lead time | R1: Production volumes | S1: Manufacturing lead time | T1: Manufacturing costs | U1: Inspection results | V1: Defect rates | W1: Transportation modes | X1: Routes | Y1: Costs | Z1: Total_Cost | AA1: Profit | AB1: Profit_Margin
A2: haircare | B2: =PROPER(TRIM(Table1[[#This Row],[Product type]])) -> Haircare | C2: SKU0 | D2: 69.808006 | E2: 55 | F2: 802 | G2: 8661.9968 | H2: Non-binary | I2: 58 | J2: 7 | K2: 96 | L2: 4 | M2: Carrier B | N2: 2.9565721 | O2: Supplier 3 | P2: Mumbai | Q2: 29 | R2: 215 | S2: 29 | T2: 46.279879 | U2: Pending | V2: 0.22641036 | W2: Road | X2: Route B | Y2: 187.75208 | Z2: =T2+N2+Y2 -> 236.98853 | AA2: =G2-Z2 -> 8425.0083 | AB2: =AA2/G2 -> 0.97264043
A3: skincare | B3: =PROPER(TRIM(Table1[[#This Row],[Product type]])) -> Skincare | C3: SKU1 | D3: 14.843523 | E3: 95 | F3: 736 | G3: 7460.9001 | H3: Female | I3: 53 | J3: 30 | K3: 37 | L3: 2 | M3: Carrier A | N3: 9.7165748 | O3: Supplier 3 | P3: Mumbai | Q3: 23 | R3: 517 | S3: 30 | T3: 33.616769 | U3: Pending | V3: 4.854068 | W3: Road | X3: Route B | Y3: 503.06558 | Z3: =T3+N3+Y3 -> 546.39892 | AA3: =G3-Z3 -> 6914.5011 | AB3: =AA3/G3 -> 0.92676501
A4: haircare | B4: =PROPER(TRIM(Table1[[#This Row],[Product type]])) -> Haircare | C4: SKU2 | D4: 11.319683 | E4: 34 | F4: 8 | G4: 9577.7496 | H4: Unknown | I4: 1 | J4: 10 | K4: 88 | L4: 2 | M4: Carrier B | N4: 8.0544793 | O4: Supplier 1 | P4: Mumbai | Q4: 12 | R4: 971 | S4: 27 | T4: 30.688019 | U4: Pending | V4: 4.5805926 | W4: Air | X4: Route C | Y4: 141.92028 | Z4: =T4+N4+Y4 -> 180.66278 | AA4: =G4-Z4 -> 9397.0868 | AB4: =AA4/G4 -> 0.98113724
A5: skincare | B5: =PROPER(TRIM(Table1[[#This Row],[Product type]])) -> Skincare | C5: SKU3 | D5: 61.163343 | E5: 68 | F5: 83 | G5: 7766.8364 | H5: Non-binary | I5: 23 | J5: 13 | K5: 59 | L5: 6 | M5: Carrier C | N5: 1.7295686 | O5: Supplier 5 | P5: Kolkata | Q5: 24 | R5: 937 | S5: 18 | T5: 35.624741 | U5: Fail | V5: 4.7466486 | W5: Rail | X5: Route A | Y5: 254.77616 | Z5: =T5+N5+Y5 -> 292.13047 | AA5: =G5-Z5 -> 7474.706 | AB5: =AA5/G5 -> 0.96238746
A6: skincare | B6: =PROPER(TRIM(Table1[[#This Row],[Product type]])) -> Skincare | C6: SKU4 | D6: 4.805496 | E6: 26 | F6: 871 | G6: 2686.5052 | H6: Non-binary | I6: 5 | J6: 3 | K6: 56 | L6: 8 | M6: Carrier A | N6: 3.8905479 | O6: Supplier 1 | P6: Delhi | Q6: 5 | R6: 414 | S6: 3 | T6: 92.065161 | U6: Fail | V6: 3.1455795 | W6: Air | X6: Route A | Y6: 923.44063 | Z6: =T6+N6+Y6 -> 1019.3963 | AA6: =G6-Z6 -> 1667.1088 | AB6: =AA6/G6 -> 0.62054927
A7: haircare | B7: =PROPER(TRIM(Table1[[#This Row],[Product type]])) -> Haircare | C7: SKU5 | D7: 1.699976 | E7: 87 | F7: 147 | G7: 2828.3487 | H7: Non-binary | I7: 90 | J7: 27 | K7: 66 | L7: 3 | M7: Carrier B | N7: 4.4440989 | O7: Supplier 4 | P7: Bangalore | Q7: 10 | R7: 104 | S7: 17 | T7: 56.766476 | U7: Fail | V7: 2.7791935 | W7: Road | X7: Route A | Y7: 235.46124 | Z7: =T7+N7+Y7 -> 296.67181 | AA7: =G7-Z7 -> 2531.6769 | AB7: =AA7/G7 -> 0.89510777
A8: skincare | B8: =PROPER(TRIM(Table1[[#This Row],[Product type]])) -> Skincare | C8: SKU6 | D8: 4.0783329 | E8: 48 | F8: 65 | G8: 7823.4766 | H8: Male | I8: 11 | J8: 15 | K8: 58 | L8: 8 | M8: Carrier C | N8: 3.8807633 | O8: Supplier 3 | P8: Kolkata | Q8: 14 | R8: 314 | S8: 24 | T8: 1.0850686 | U8: Pending | V8: 1.0009106 | W8: Sea | X8: Route A | Y8: 134.3691 | Z8: =T8+N8+Y8 -> 139.33493 | AA8: =G8-Z8 -> 7684.1416 | AB8: =AA8/G8 -> 0.98219015
A9: cosmetics | B9: =PROPER(TRIM(Table1[[#This Row],[Product type]])) -> Cosmetics | C9: SKU7 | D9: 42.958384 | E9: 59 | F9: 426 | G9: 8496.1038 | H9: Female | I9: 93 | J9: 17 | K9: 11 | L9: 1 | M9: Carrier B | N9: 2.3483388 | O9: Supplier 4 | P9: Bangalore | Q9: 22 | R9: 564 | S9: 1 | T9: 99.466109 | U9: Fail | V9: 0.39817719 | W9: Road | X9: Route C | Y9: 802.05631 | Z9: =T9+N9+Y9 -> 903.87076 | AA9: =G9-Z9 -> 7592.2331 | AB9: =AA9/G9 -> 0.8936135
A10: cosmetics | B10: =PROPER(TRIM(Table1[[#This Row],[Product type]])) -> Cosmetics | C10: SKU8 | D10: 68.717597 | E10: 78 | F10: 150 | G10: 7517.3632 | H10: Female | I10: 5 | J10: 10 | K10: 15 | L10: 7 | M10: Carrier C | N10: 3.4047339 | O10: Supplier 4 | P10: Mumbai | Q10: 13 | R10: 769 | S10: 8 | T10: 11.423027 | U10: Pending | V10: 2.7098627 | W10: Sea | X10: Route B | Y10: 505.55713 | Z10: =T10+N10+Y10 -> 520.3849 | AA10: =G10-Z10 -> 6996.9783 | AB10: =AA10/G10 -> 0.93077561
A11: skincare | B11: =PROPER(TRIM(Table1[[#This Row],[Product type]])) -> Skincare | C11: SKU9 | D11: 64.015733 | E11: 35 | F11: 980 | G11: 4971.146 | H11: Unknown | I11: 14 | J11: 27 | K11: 83 | L11: 1 | M11: Carrier A | N11: 7.1666453 | O11: Supplier 2 | P11: Chennai | Q11: 29 | R11: 963 | S11: 23 | T11: 47.957602 | U11: Pending | V11: 3.8446145 | W11: Rail | X11: Route B | Y11: 995.92946 | Z11: =T11+N11+Y11 -> 1051.0537 | AA11: =G11-Z11 -> 3920.0923 | AB11: =AA11/G11 -> 0.78856913
A12: skincare | B12: =PROPER(TRIM(Table1[[#This Row],[Product type]])) -> Skincare | C12: SKU10 | D12: 15.707796 | E12: 11 | F12: 996 | G12: 2330.9658 | H12: Non-binary | I12: 51 | J12: 13 | K12: 80 | L12: 2 | M12: Carrier C | N12: 8.6732112 | O12: Supplier 5 | P12: Kolkata | Q12: 18 | R12: 830 | S12: 5 | T12: 96.527353 | U12: Pass | V12: 1.7273139 | W12: Road | X12: Route B | Y12: 806.10318 | Z12: =T12+N12+Y12 -> 911.30374 | AA12: =G12-Z12 -> 1419.6621 | AB12: =AA12/G12 -> 0.60904457
A13: skincare | B13: =PROPER(TRIM(Table1[[#This Row],[Product type]])) -> Skincare | C13: SKU11 | D13: 90.63546 | E13: 95 | F13: 960 | G13: 6099.9441 | H13: Female | I13: 46 | J13: 23 | K13: 60 | L13: 1 | M13: Carrier A | N13: 4.5239431 | O13: Supplier 2 | P13: Kolkata | Q13: 28 | R13: 362 | S13: 11 | T13: 27.592363 | U13: Pending | V13: 0.021169821 | W13: Air | X13: Route A | Y13: 126.72303 | Z13: =T13+N13+Y13 -> 158.83934 | AA13: =G13-Z13 -> 5941.1048 | AB13: =AA13/G13 -> 0.97396053
... A101: haircare | B101: =PROPER(TRIM(Table1[[#This Row],[Product type]])) -> Haircare | C101: SKU99 | D101: 68.517833 | E101: 17 | F101: 627 | G101: 9185.1858 | H101: Unknown | I101: 55 | J101: 8 | K101: 59 | L101: 6 | M101: Carrier B | N101: 1.3110238 | O101: Supplier 2 | P101: Chennai | Q101: 29 | R101: 921 | S101: 2 | T101: 38.072899 | U101: Fail | V101: 0.34602729 | W101: Rail | X101: Route B | Y101: 210.74301 | Z101: =T101+N101+Y101 -> 250.12693 | AA101: =G101-Z101 -> 8935.0589 | AB101: =AA101/G101 -> 0.97276844

Sheet 04_CLEANED_DATA
A1: Product_Type | B1: SKU | C1: Price | D1: Availability | E1: Number_of_Products _Sold | F1: Revenue_Generated | G1: Customer_Demographics | H1: Stock_Levels | I1: Lead_Times | J1: Order_Quantities | K1: Shipping_Times | L1: Shipping_Carriers | M1: Shipping_Costs | N1: Supplier_Name | O1: Location | P1: Lead_Time | Q1: Production_Volumes | R1: Manufacturing_Lead_Time | S1: Manufacturing_Costs | T1: Inspection_Results | U1: Defect_Rates | V1: Transportation_Modes | W1: Routes | X1: Costs | Y1: Total_Cost | Z1: Profit | AA1: Profit_Margin
A2: Haircare | B2: SKU0 | C2: 69.808006 | D2: 55 | E2: 802 | F2: 8661.9968 | G2: Non-binary | H2: 58 | I2: 7 | J2: 96 | K2: 4 | L2: Carrier B | M2: 2.9565721 | N2: Supplier 3 | O2: Mumbai | P2: 29 | Q2: 215 | R2: 29 | S2: 46.279879 | T2: Pending | U2: 0.22641036 | V2: Road | W2: Route B | X2: 187.75208 | Y2: 236.98853 | Z2: 8425.0083 | AA2: 0.97264043
A3: Skincare | B3: SKU1 | C3: 14.843523 | D3: 95 | E3: 736 | F3: 7460.9001 | G3: Female | H3: 53 | I3: 30 | J3: 37 | K3: 2 | L3: Carrier A | M3: 9.7165748 | N3: Supplier 3 | O3: Mumbai | P3: 23 | Q3: 517 | R3: 30 | S3: 33.616769 | T3: Pending | U3: 4.854068 | V3: Road | W3: Route B | X3: 503.06558 | Y3: 546.39892 | Z3: 6914.5011 | AA3: 0.92676501
A4: Haircare | B4: SKU2 | C4: 11.319683 | D4: 34 | E4: 8 | F4: 9577.7496 | G4: Unknown | H4: 1 | I4: 10 | J4: 88 | K4: 2 | L4: Carrier B | M4: 8.0544793 | N4: Supplier 1 | O4: Mumbai | P4: 12 | Q4: 971 | R4: 27 | S4: 30.688019 | T4: Pending | U4: 4.5805926 | V4: Air | W4: Route C | X4: 141.92028 | Y4: 180.66278 | Z4: 9397.0868 | AA4: 0.98113724
A5: Skincare | B5: SKU3 | C5: 61.163343 | D5: 68 | E5: 83 | F5: 7766.8364 | G5: Non-binary | H5: 23 | I5: 13 | J5: 59 | K5: 6 | L5: Carrier C | M5: 1.7295686 | N5: Supplier 5 | O5: Kolkata | P5: 24 | Q5: 937 | R5: 18 | S5: 35.624741 | T5: Fail | U5: 4.7466486 | V5: Rail | W5: Route A | X5: 254.77616 | Y5: 292.13047 | Z5: 7474.706 | AA5: 0.96238746
A6: Skincare | B6: SKU4 | C6: 4.805496 | D6: 26 | E6: 871 | F6: 2686.5052 | G6: Non-binary | H6: 5 | I6: 3 | J6: 56 | K6: 8 | L6: Carrier A | M6: 3.8905479 | N6: Supplier 1 | O6: Delhi | P6: 5 | Q6: 414 | R6: 3 | S6: 92.065161 | T6: Fail | U6: 3.1455795 | V6: Air | W6: Route A | X6: 923.44063 | Y6: 1019.3963 | Z6: 1667.1088 | AA6: 0.62054927
A7: Haircare | B7: SKU5 | C7: 1.699976 | D7: 87 | E7: 147 | F7: 2828.3487 | G7: Non-binary | H7: 90 | I7: 27 | J7: 66 | K7: 3 | L7: Carrier B | M7: 4.4440989 | N7: Supplier 4 | O7: Bangalore | P7: 10 | Q7: 104 | R7: 17 | S7: 56.766476 | T7: Fail | U7: 2.7791935 | V7: Road | W7: Route A | X7: 235.46124 | Y7: 296.67181 | Z7: 2531.6769 | AA7: 0.89510777
A8: Skincare | B8: SKU6 | C8: 4.0783329 | D8: 48 | E8: 65 | F8: 7823.4766 | G8: Male | H8: 11 | I8: 15 | J8: 58 | K8: 8 | L8: Carrier C | M8: 3.8807633 | N8: Supplier 3 | O8: Kolkata | P8: 14 | Q8: 314 | R8: 24 | S8: 1.0850686 | T8: Pending | U8: 1.0009106 | V8: Sea | W8: Route A | X8: 134.3691 | Y8: 139.33493 | Z8: 7684.1416 | AA8: 0.98219015
A9: Cosmetics | B9: SKU7 | C9: 42.958384 | D9: 59 | E9: 426 | F9: 8496.1038 | G9: Female | H9: 93 | I9: 17 | J9: 11 | K9: 1 | L9: Carrier B | M9: 2.3483388 | N9: Supplier 4 | O9: Bangalore | P9: 22 | Q9: 564 | R9: 1 | S9: 99.466109 | T9: Fail | U9: 0.39817719 | V9: Road | W9: Route C | X9: 802.05631 | Y9: 903.87076 | Z9: 7592.2331 | AA9: 0.8936135
A10: Cosmetics | B10: SKU8 | C10: 68.717597 | D10: 78 | E10: 150 | F10: 7517.3632 | G10: Female | H10: 5 | I10: 10 | J10: 15 | K10: 7 | L10: Carrier C | M10: 3.4047339 | N10: Supplier 4 | O10: Mumbai | P10: 13 | Q10: 769 | R10: 8 | S10: 11.423027 | T10: Pending | U10: 2.7098627 | V10: Sea | W10: Route B | X10: 505.55713 | Y10: 520.3849 | Z10: 6996.9783 | AA10: 0.93077561
A11: Skincare | B11: SKU9 | C11: 64.015733 | D11: 35 | E11: 980 | F11: 4971.146 | G11: Unknown | H11: 14 | I11: 27 | J11: 83 | K11: 1 | L11: Carrier A | M11: 7.1666453 | N11: Supplier 2 | O11: Chennai | P11: 29 | Q11: 963 | R11: 23 | S11: 47.957602 | T11: Pending | U11: 3.8446145 | V11: Rail | W11: Route B | X11: 995.92946 | Y11: 1051.0537 | Z11: 3920.0923 | AA11: 0.78856913
A12: Skincare | B12: SKU10 | C12: 15.707796 | D12: 11 | E12: 996 | F12: 2330.9658 | G12: Non-binary | H12: 51 | I12: 13 | J12: 80 | K12: 2 | L12: Carrier C | M12: 8.6732112 | N12: Supplier 5 | O12: Kolkata | P12: 18 | Q12: 830 | R12: 5 | S12: 96.527353 | T12: Pass | U12: 1.7273139 | V12: Road | W12: Route B | X12: 806.10318 | Y12: 911.30374 | Z12: 1419.6621 | AA12: 0.60904457
A13: Skincare | B13: SKU11 | C13: 90.63546 | D13: 95 | E13: 960 | F13: 6099.9441 | G13: Female | H13: 46 | I13: 23 | J13: 60 | K13: 1 | L13: Carrier A | M13: 4.5239431 | N13: Supplier 2 | O13: Kolkata | P13: 28 | Q13: 362 | R13: 11 | S13: 27.592363 | T13: Pending | U13: 0.021169821 | V13: Air | W13: Route A | X13: 126.72303 | Y13: 158.83934 | Z13: 5941.1048 | AA13: 0.97396053
... A101: Haircare | B101: SKU99 | C101: 68.517833 | D101: 17 | E101: 627 | F101: 9185.1858 | G101: Unknown | H101: 55 | I101: 8 | J101: 59 | K101: 6 | L101: Carrier B | M101: 1.3110238 | N101: Supplier 2 | O101: Chennai | P101: 29 | Q101: 921 | R101: 2 | S101: 38.072899 | T101: Fail | U101: 0.34602729 | V101: Rail | W101: Route B | X101: 210.74301 | Y101: 250.12693 | Z101: 8935.0589 | AA101: 0.97276844

Sheet 05_PIVOT_TABLES
A2: Sum of Revenue_Generated | C2: Sum of Total_Cost | E2: Sum of Profit | G2: Sum of Number_of_Products _Sold | I2: Average of Profit_Margin | L2: Product_Type | M2: Sum of Revenue_Generated | P2: Product_Type | Q2: Sum of Profit | U2: Product_Type | V2: Revenue | W2: Total Cost | AA2: Product_Type | AB2: Average of Profit_Margin | AE2: SKU | AF2: Sum of Revenue_Generated | AI2: SKU | AJ2: Sum of Stock_Levels | AM2: Average of Defect_Rates | AN2: Column Labels | AS2: Product_Type | AT2: Average of Costs | AW2: Shipping_Carriers | AX2: Sum of Shipping_Costs
A3: 577604.82 | C3: 58206.062 | E3: 519398.76 | G3: 46099 | I3: 0.86066707 | L3: Skincare | M3: 241628.16 | P3: Skincare | Q3: 217242.73 | U3: Skincare | V3: 241628.16 | W3: 24385.432 | AA3: Cosmetics | AB3: 0.87262753 | AE3: SKU18 | AF3: 9364.6735 | AI3: SKU45 | AJ3: 93 | AM3: Transportation_Modes | AN3: Cosmetics | AO3: Haircare | AP3: Skincare | AQ3: Grand Total | AS3: Route B | AT3: 595.65903 | AW3: Carrier B | AX3: 236.89762
L4: Haircare | M4: 174455.39 | P4: Haircare | Q4: 155278.09 | U4: Haircare | V4: 174455.39 | W4: 19177.298 | AA4: Skincare | AB4: 0.85979638 | AE4: SKU52 | AF4: 9435.7626 | AI4: SKU7 | AJ4: 93 | AM4: Air | AN4: 0.39938126 | AO4: 2.9247088 | AP4: 1.6944181 | AQ4: 1.8239235 | AS4: Route C | AT4: 500.47098 | AW4: Carrier C | AX4: 162.37946
L5: Cosmetics | M5: 161521.27 | P5: Cosmetics | Q5: 146877.93 | U5: Cosmetics | V5: 161521.27 | W5: 14643.332 | AA5: Haircare | AB5: 0.85254519 | AE5: SKU88 | AF5: 9444.742 | AI5: SKU69 | AJ5: 95 | AM5: Rail | AN5: 2.158841 | AO5: 1.959318 | AP5: 2.8782267 | AQ5: 2.3188139 | AS5: Route A | AT5: 485.48313 | AW5: Carrier A | AX5: 155.53783
L6: Grand Total | M6: 577604.82 | P6: Grand Total | Q6: 519398.76 | U6: Grand Total | V6: 577604.82 | W6: 58206.062 | AA6: Grand Total | AB6: 0.86066707 | AE6: SKU67 | AF6: 9473.798 | AI6: SKU53 | AJ6: 96 | AM6: Road | AN6: 2.7036749 | AO6: 2.2387316 | AP6: 2.9927625 | AQ6: 2.6209385 | AS6: Grand Total | AT6: 529.24578 | AW6: Grand Total | AX6: 554.81491
AE7: SKU32 | AF7: 9571.5505 | AI7: SKU77 | AJ7: 96 | AM7: Sea | AN7: 2.0421561 | AO7: 3.6428695 | AP7: 1.7907668 | AQ7: 2.3152813
AE8: SKU2 | AF8: 9577.7496 | AI8: SKU55 | AJ8: 97 | AM8: Grand Total | AN8: 1.919287 | AO8: 2.4831502 | AP8: 2.3346808 | AQ8: 2.277158
AE9: SKU90 | AF9: 9592.6336 | AI9: SKU49 | AJ9: 97
AE10: SKU31 | AF10: 9655.1351 | AI10: SKU91 | AJ10: 98
AE11: SKU38 | AF11: 9692.318 | AI11: SKU59 | AJ11: 100
AE12: SKU51 | AF12: 9866.4655 | AI12: SKU12 | AJ12: 100
AE13: Grand Total | AF13: 95674.828 | AI13: SKU51 | AJ13: 100
AI14: Grand Total | AJ14: 1065

Sheet 06_DASHBOARD
B7: =GETPIVOTDATA("Revenue_Generated",'05_PIVOT_TABLES'!$A$2) -> 577604.82 | H7: =GETPIVOTDATA("Total_Cost",'05_PIVOT_TABLES'!$C$2) -> 58206.062 | N7: =GETPIVOTDATA("Profit",'05_PIVOT_TABLES'!$E$2) -> 519398.76 | S7: =GETPIVOTDATA("Number_of_Products _Sold",'05_PIVOT_TABLES'!$G$2) -> 46099 | Y7: =GETPIVOTDATA("Profit_Margin",'05_PIVOT_TABLES'!$I$2) -> 0.86066707
